chirper/__init__.py
chirper/__main__.py
chirper/config.py
chirper/exceptions.py
chirper/api/__init__.py
chirper/api/chirp.py
chirper/api/data_handler.py
chirper/api/data_process.py
chirper/api/input_source.py
chirper/api/request_handler.py
chirper/gui/__init__.py
chirper/gui/main_gui.py
chirper/modulation/__init__.py
chirper/modulation/am.py
chirper/modulation/fm.py
chirper/modulation/pm.py
chirper/sgn/__init__.py
chirper/sgn/signal.py
chirper/sgn/signal1.py
chirper/sgn/signal2.py
chirper/sgn/defaults/__init__.py
chirper/sgn/defaults/default1.py
chirper/sgn/handlers/__init__.py
chirper/sgn/handlers/handler_csv.py
chirper/sgn/handlers/handler_img.py
chirper/sgn/handlers/handler_json.py
chirper/sgn/handlers/handler_wav.py
chirper/test/__init__.py
chirper/test/manual_tests.py
chirper/test/unit_tests.py
chirper/test/manual/__init__.py
chirper/test/manual/manual_am_modulation.py
chirper/test/manual/manual_conv1.py
chirper/test/manual/manual_conv2.py
chirper/test/manual/manual_cos1.py
chirper/test/manual/manual_cos2.py
chirper/test/manual/manual_fourier1.py
chirper/test/manual/manual_fourier2.py
chirper/test/manual/manual_hilbert.py
chirper/test/manual/manual_interp1.py
chirper/test/manual/manual_io1.py
chirper/test/manual/manual_io2.py
chirper/test/manual/manual_modulation.py
chirper/test/manual/manual_sin1.py
chirper/test/manual/manual_spectr.py
chirper/test/unit/__init__.py
chirper/test/unit/sgn/__init__.py
chirper/test/unit/sgn/test_signal.py
chirper/transforms/__init__.py
chirper/transforms/cosine.py
chirper/transforms/fourier.py
chirper/transforms/hilbert.py
chirper/transforms/ifourier.py
chirper/transforms/sine.py
chirper/transforms/stft.py
chirper/transforms/wavelet.py
chirper/transforms/z.py
chirper/utils/__init__.py
chirper/utils/file_handling.py
chirper/utils/kernel.py
chirper/utils/math_lib.py
chirper/utils/window.py
chirper_py-1.1.4.dist-info/LICENSE
chirper_py-1.1.4.dist-info/METADATA
chirper_py-1.1.4.dist-info/WHEEL
chirper_py-1.1.4.dist-info/top_level.txt
chirper_py-1.1.4.dist-info/RECORD
