Metadata-Version: 2.1
Name: chirper-py
Version: 1.1.4
Summary: Package for signal analysis
Home-page: https://github.com/No-tengo-nombre/chirper
Author: Cristobal Allendes
Author-email: callendes.molina@gmail.com
License: UNKNOWN
Platform: UNKNOWN
Classifier: Programming Language :: Python :: 3
Classifier: License :: OSI Approved :: GNU General Public License v3 (GPLv3)
Classifier: Operating System :: OS Independent
Requires-Python: >=3.8
License-File: LICENSE
